freshbooks/__init__.py
freshbooks/client.py
freshbooks/exceptions.py
freshbooks/httpx_client.py
freshbooks/model/__init__.py
freshbooks/model/business.py
freshbooks/model/identity.py
python_freshbooks-0.7.2.dist-info/LICENSE
python_freshbooks-0.7.2.dist-info/METADATA
python_freshbooks-0.7.2.dist-info/WHEEL
python_freshbooks-0.7.2.dist-info/top_level.txt
python_freshbooks-0.7.2.dist-info/RECORD
