Metadata-Version: 2.1
Name: python-freshbooks
Version: 0.7.2
Summary: Python wrapper for the FreshBooks API
Home-page: https://github.com/alexbaizeau/python-freshbooks
Author-email: alexandre.baizeau@gmail.com
License: MIT License
Platform: UNKNOWN
License-File: LICENSE
Requires-Dist: authlib
